setup.cfg
setup.py
navitia_client/__init__.py
navitia_client/client.py
navitia_client/departures.py
navitia_client/exceptions.py
navitia_client/explore.py
navitia_client/inverted_geocoding.py
navitia_client/isochrones.py
navitia_client/journeys.py
navitia_client/parser.py
navitia_client/places_nearby.py
navitia_client/raw.py
navitia_client/route_schedules.py
navitia_client/utils.py
navitia_client.egg-info/PKG-INFO
navitia_client.egg-info/SOURCES.txt
navitia_client.egg-info/dependency_links.txt
navitia_client.egg-info/top_level.txt
test/test_client.py
test/test_departures.py
test/test_explore.py
test/test_inverted_geocoding.py
test/test_journeys.py
test/test_raw.py
test/test_route_schedules.py