Metadata-Version: 1.0
Name: navitia-client
Version: 0.4
Summary: Navitia client for python
Home-page: https://github.com/leonardbinet/navitia-python
Author: Leonard Binet
Author-email: leonardbinet@gmail.com
License: MIT
Platform: UNKNOWN
